CHANGELOG.md
LICENSE
README.md
fastapi_admin/__init__.py
fastapi_admin/app.py
fastapi_admin/constants.py
fastapi_admin/depends.py
fastapi_admin/enums.py
fastapi_admin/exceptions.py
fastapi_admin/file_upload.py
fastapi_admin/i18n.py
fastapi_admin/locales/en_US/LC_MESSAGES/messages.po
fastapi_admin/locales/zh_CN/LC_MESSAGES/messages.po
fastapi_admin/middlewares.py
fastapi_admin/models.py
fastapi_admin/providers/__init__.py
fastapi_admin/providers/login.py
fastapi_admin/resources.py
fastapi_admin/responses.py
fastapi_admin/routes/__init__.py
fastapi_admin/routes/resources.py
fastapi_admin/template.py
fastapi_admin/templates/base.html
fastapi_admin/templates/components/alert_error.html
fastapi_admin/templates/components/dropdown-show.html
fastapi_admin/templates/components/dropdown.html
fastapi_admin/templates/components/footer.html
fastapi_admin/templates/components/language.html
fastapi_admin/templates/components/link.html
fastapi_admin/templates/components/model.html
fastapi_admin/templates/components/select.html
fastapi_admin/templates/create.html
fastapi_admin/templates/errors/401.html
fastapi_admin/templates/errors/403.html
fastapi_admin/templates/errors/404.html
fastapi_admin/templates/errors/500.html
fastapi_admin/templates/errors/maintenance.html
fastapi_admin/templates/init.html
fastapi_admin/templates/layout.html
fastapi_admin/templates/list.html
fastapi_admin/templates/providers/login/avatar.html
fastapi_admin/templates/providers/login/login.html
fastapi_admin/templates/providers/login/password.html
fastapi_admin/templates/update.html
fastapi_admin/templates/widgets/displays/boolean.html
fastapi_admin/templates/widgets/displays/image.html
fastapi_admin/templates/widgets/displays/json.html
fastapi_admin/templates/widgets/filters/datetime.html
fastapi_admin/templates/widgets/filters/search.html
fastapi_admin/templates/widgets/filters/select.html
fastapi_admin/templates/widgets/inputs/color.html
fastapi_admin/templates/widgets/inputs/editor.html
fastapi_admin-1.0.3.dist-info/LICENSE
fastapi_admin-1.0.3.dist-info/WHEEL
fastapi_admin-1.0.3.dist-info/METADATA
fastapi_admin-1.0.3.dist-info/RECORD
